brevo_dc_cli/__init__.py
brevo_dc_cli/cli.py
brevo_dc_cli/cli_datacontract_cmd.py
brevo_dc_cli/common/__init__.py
brevo_dc_cli/common/log.py
brevo_dc_cli/helper/__init__.py
brevo_dc_cli/helper/datacontract_helper.py
brevo_dc_cli/helper/secret_manager_helper.py
brevo_dc_cli-0.1.5.dist-info/METADATA
brevo_dc_cli-0.1.5.dist-info/WHEEL
brevo_dc_cli-0.1.5.dist-info/entry_points.txt
brevo_dc_cli-0.1.5.dist-info/top_level.txt
brevo_dc_cli-0.1.5.dist-info/RECORD
