Metadata-Version: 2.1
Name: brevo-dc-cli
Version: 0.1.5
Summary: datacontract CLI for Brevo's data team
Home-page: 
Author: Filah Anas
Author-email: anas.filah@brevo.com
Requires-Dist: deltalake
Requires-Dist: datacontract-cli ==0.10.9
Requires-Dist: pyspark ==3.5.1
Requires-Dist: google-cloud-secret-manager ==2.16.0
Requires-Dist: soda-core-bigquery
